<annotation>
	<folder>images</folder>
	<filename>medium_fatty_tuna_30bd8a48e316cd89f485f73234d2d0f1.jpg</filename>
	<path>/Users/junji/Development/sushi_detector_dataset/images/medium_fatty_tuna_30bd8a48e316cd89f485f73234d2d0f1.jpg</path>
	<source>
		<database>Unknown</database>
	</source>
	<size>
		<width>640</width>
		<height>332</height>
		<depth>3</depth>
	</size>
	<segmented>0</segmented>
	<object>
		<name>medium_fatty_tuna</name>
		<pose>Unspecified</pose>
		<truncated>0</truncated>
		<difficult>0</difficult>
		<bndbox>
			<xmin>55</xmin>
			<ymin>26</ymin>
			<xmax>532</xmax>
			<ymax>324</ymax>
		</bndbox>
	</object>
</annotation>
