<annotation>
	<folder>images</folder>
	<filename>medium-fatty-tuna_6a4002d1050820f74f5600b52b1de8f6.jpg</filename>
	<path>/Users/junji/Development/sushi_detector_dataset/data/images/medium-fatty-tuna_6a4002d1050820f74f5600b52b1de8f6.jpg</path>
	<source>
		<database>Unknown</database>
	</source>
	<size>
		<width>640</width>
		<height>360</height>
		<depth>3</depth>
	</size>
	<segmented>0</segmented>
	<object>
		<name>medium-fatty-tuna</name>
		<pose>Unspecified</pose>
		<truncated>0</truncated>
		<difficult>0</difficult>
		<bndbox>
			<xmin>164</xmin>
			<ymin>114</ymin>
			<xmax>472</xmax>
			<ymax>308</ymax>
		</bndbox>
	</object>
</annotation>
