<annotation>
	<folder>images</folder>
	<filename>medium-fatty-tuna_d5ee520b423d600b89ab2bbb62f7bb4c.jpg</filename>
	<path>/Users/junji/Development/sushi_detector_dataset/data/images/medium-fatty-tuna_d5ee520b423d600b89ab2bbb62f7bb4c.jpg</path>
	<source>
		<database>Unknown</database>
	</source>
	<size>
		<width>640</width>
		<height>360</height>
		<depth>3</depth>
	</size>
	<segmented>0</segmented>
	<object>
		<name>medium-fatty-tuna</name>
		<pose>Unspecified</pose>
		<truncated>0</truncated>
		<difficult>0</difficult>
		<bndbox>
			<xmin>51</xmin>
			<ymin>95</ymin>
			<xmax>475</xmax>
			<ymax>295</ymax>
		</bndbox>
	</object>
</annotation>
