<annotation>
	<folder>images</folder>
	<filename>medium_fatty_tuna_62cb3b7b78da1efa7ce5a0fb52ef06bf.jpg</filename>
	<path>/Users/junji/Development/sushi_detector_dataset/images/medium_fatty_tuna_62cb3b7b78da1efa7ce5a0fb52ef06bf.jpg</path>
	<source>
		<database>Unknown</database>
	</source>
	<size>
		<width>640</width>
		<height>360</height>
		<depth>3</depth>
	</size>
	<segmented>0</segmented>
	<object>
		<name>medium_fatty_tuna</name>
		<pose>Unspecified</pose>
		<truncated>0</truncated>
		<difficult>0</difficult>
		<bndbox>
			<xmin>401</xmin>
			<ymin>96</ymin>
			<xmax>470</xmax>
			<ymax>234</ymax>
		</bndbox>
	</object>
</annotation>
