<annotation>
	<folder>images</folder>
	<filename>salmon_1c34c1b810dfdbeb697b17fd0e99d475.jpg</filename>
	<path>/Users/junji/Development/sushi_detector_dataset/data/images/salmon_1c34c1b810dfdbeb697b17fd0e99d475.jpg</path>
	<source>
		<database>Unknown</database>
	</source>
	<size>
		<width>640</width>
		<height>360</height>
		<depth>3</depth>
	</size>
	<segmented>0</segmented>
	<object>
		<name>salmon</name>
		<pose>Unspecified</pose>
		<truncated>0</truncated>
		<difficult>0</difficult>
		<bndbox>
			<xmin>60</xmin>
			<ymin>123</ymin>
			<xmax>560</xmax>
			<ymax>318</ymax>
		</bndbox>
	</object>
</annotation>
