<annotation>
	<folder>salmon</folder>
	<filename>salmon_532bdb8c4066c82da732caf07801b50e.jpg</filename>
	<path>/Users/junji/Development/sushi_detector_dataset/images/salmon_532bdb8c4066c82da732caf07801b50e.jpg</path>
	<source>
		<database>Unknown</database>
	</source>
	<size>
		<width>640</width>
		<height>427</height>
		<depth>3</depth>
	</size>
	<segmented>0</segmented>
	<object>
		<name>salmon</name>
		<pose>Unspecified</pose>
		<truncated>0</truncated>
		<difficult>0</difficult>
		<bndbox>
			<xmin>112</xmin>
			<ymin>143</ymin>
			<xmax>374</xmax>
			<ymax>282</ymax>
		</bndbox>
	</object>
</annotation>
